py_jitutils/__init__.py
py_jitutils/jitutils.py
pyjitutils-1.0.1.dist-info/METADATA
pyjitutils-1.0.1.dist-info/WHEEL
pyjitutils-1.0.1.dist-info/top_level.txt
pyjitutils-1.0.1.dist-info/RECORD
