Metadata-Version: 2.1
Name: pyjitutils
Version: 1.0.1
Summary: timestamp convert to datetime
Home-page: https://PichaiLimpanitivat@bitbucket.org/python-package/pyjitutils.git
Author: PichaiLim
Author-email: Pichai.Limpanitivat@gmail.com
License: UNKNOWN
Keywords: pyJitUtils jitutils src convert timestamp datetime
Platform: UNKNOWN
Requires-Python: >=3.6
Requires-Dist: attrs (==20.3.0)
Requires-Dist: certifi (==2020.12.5)
Requires-Dist: chardet (==4.0.0)
Requires-Dist: idna (==2.10)
Requires-Dist: iniconfig (==1.1.1)
Requires-Dist: packaging (==20.9)
Requires-Dist: pluggy (==0.13.1)
Requires-Dist: py (==1.10.0)
Requires-Dist: pyparsing (==2.4.7)
Requires-Dist: pytest (==6.2.3)
Requires-Dist: requests (==2.25.1)
Requires-Dist: toml (==0.10.2)
Requires-Dist: tzdata (==2021.1)
Requires-Dist: urllib3 (==1.26.4)
